taskgraph/Task.py
taskgraph/__init__.py
taskgraph-0.11.2.dist-info/licenses/LICENSE.txt
taskgraph-0.11.2.dist-info/METADATA
taskgraph-0.11.2.dist-info/WHEEL
taskgraph-0.11.2.dist-info/top_level.txt
taskgraph-0.11.2.dist-info/RECORD
