Metadata-Version: 2.4
Name: taskgraph
Version: 0.11.2
Summary: Parallel task graph framework
Home-page: https://github.com/natcap/taskgraph
Maintainer: Natural Capital Project Software Team
License: In this license, "Natural Capital Project" is defined as the parties of
Keywords: parallel,multiprocessing,distributed,computing
Classifier: Intended Audience :: Developers
Classifier: Topic :: System :: Distributed Computing
Classifier: Development Status :: 5 - Production/Stable
Classifier: Natural Language :: English
Classifier: Operating System :: MacOS :: MacOS X
Classifier: Operating System :: Microsoft
Classifier: Operating System :: POSIX
Classifier: Programming Language :: Python :: 3.8
Classifier: Programming Language :: Python :: 3.9
Classifier: Programming Language :: Python :: 3.10
Classifier: Programming Language :: Python :: 3.11
Classifier: Programming Language :: Python :: 3.12
Classifier: License :: OSI Approved :: BSD License
Requires-Python: >=3.6
License-File: LICENSE.txt
Requires-Dist: retrying>=1.3.0
Requires-Dist: importlib_metadata
Provides-Extra: niced-processes
Requires-Dist: psutil; extra == "niced-processes"
Dynamic: home-page
Dynamic: license-file
Dynamic: provides-extra
Dynamic: requires-dist
